source/decode/control_unit.sv
module control_unit (
    input   logic [6:0]     i_op,
    input   logic [2:0]     i_func3,
    input   logic [6:0]     i_func7,

    output  logic           reg_wrD,     
    output  logic [1:0]     result_srcD, 
    output  logic           mem_wrD,     
    output  logic           jumpD,      
    output  logic           branchD,    
    output  logic [3:0]     alu_ctrlD,  
    output  logic           alu_srcAD,
    output  logic           alu_srcBD   );


    localparam [6:0] op_RTYPE = 7'b0110011,  
                     op_ITYPE = 7'b0010011,  
                     op_LOAD  = 7'b0000011,  
                     op_STORE = 7'b0100011,  
                     op_BRANCH= 7'b1100011,  
                     op_JAL   = 7'b1101111,  
                     op_JALR  = 7'b1100111,  
                     op_LUI   = 7'b0110111,  
                     op_AUIPC = 7'b0010111;        
    localparam [3:0] func_ADD  = 4'b0_000,
                     func_SUB  = 4'b1_000,
                     func_SLL  = 4'b0_001,
                     func_SLT  = 4'b0_010,
                     func_SLTU = 4'b0_011,
                     func_XOR  = 4'b0_100,
                     func_SRL  = 4'b0_101,
                     func_SRA  = 4'b1_101,
                     func_OR   = 4'b0_110,   
                     func_AND  = 4'b0_111;
    localparam [2:0]
                     func_BEQ  = 3'b000,   
                     func_BNE  = 3'b001,   
                     func_BLT  = 3'b100,   
                     func_BGE  = 3'b101,   
                     func_BLTU = 3'b110,   
                     func_BGEU = 3'b111;   
 
    always_comb begin
        if(i_op == 7'b0000000) begin
            {reg_wrD, result_srcD, mem_wrD, jumpD, branchD, alu_ctrlD, alu_srcAD, alu_srcBD} = {1'b0, 2'b00, 1'b0, 1'b0, 1'b0, 4'd0, 1'b0, 1'b0};
        end
        else begin
        case(i_op) 

            op_RTYPE: begin
                      {reg_wrD, result_srcD, mem_wrD, jumpD, branchD, alu_srcAD, alu_srcBD} = {1'b1, 2'b00, 1'b0, 1'b0, 1'b0, 1'b0, 1'b0};
                        case({i_func7[5],i_func3})
                            func_ADD:   alu_ctrlD = 4'd0;
                            func_SUB:   alu_ctrlD = 4'd1;
                            func_SLL:   alu_ctrlD = 4'd2;
                            func_SRL:   alu_ctrlD = 4'd3;    
                            func_XOR:   alu_ctrlD = 4'd4;
                            func_AND:   alu_ctrlD = 4'd5;
                            func_OR:    alu_ctrlD = 4'd6;
                            func_SLT:   alu_ctrlD = 4'd7;
                            func_SLTU:  alu_ctrlD = 4'd8;
                            func_SRA:   alu_ctrlD = 4'd9;
                            default:    alu_ctrlD = 4'd0;
                        endcase                
                end
            op_ITYPE: begin
                      {reg_wrD, result_srcD, mem_wrD, jumpD, branchD, alu_srcAD, alu_srcBD} = {1'b1, 2'b00, 1'b0, 1'b0, 1'b0, 1'b0, 1'b1}; 
                        case({i_func7[5],i_func3})
                            func_ADD:   alu_ctrlD = 4'd0;
                            func_SLL:   alu_ctrlD = 4'd2;
                            func_SRL:   alu_ctrlD = 4'd3;    
                            func_XOR:   alu_ctrlD = 4'd4;
                            func_AND:   alu_ctrlD = 4'd5;
                            func_OR:    alu_ctrlD = 4'd6;
                            func_SLT:   alu_ctrlD = 4'd7;
                            func_SLTU:  alu_ctrlD = 4'd8;
                            func_SRA:   alu_ctrlD = 4'd9;
                            default:    alu_ctrlD = 4'd0;
                        endcase                     
                end  
            op_BRANCH: begin
                      {reg_wrD, result_srcD, mem_wrD, jumpD, branchD, alu_srcAD, alu_srcBD} = {1'b0, 2'b00, 1'b0, 1'b0, 1'b1, 1'b0, 1'b0};   
                      case ({1'b0,i_func3})
                            func_BNE:   alu_ctrlD = 4'd7;   
                            func_BNE:   alu_ctrlD = 4'd7;
                            func_BLT:   alu_ctrlD = 4'd7;
                            func_BGE:   alu_ctrlD = 4'd7;
                            func_BLTU:  alu_ctrlD = 4'd8; 
                            func_BGEU:  alu_ctrlD = 4'd8;
                            default:    alu_ctrlD = 4'd0;
                      endcase
            end
            op_LOAD:  {reg_wrD, result_srcD, mem_wrD, jumpD, branchD, alu_ctrlD, alu_srcAD, alu_srcBD} = {1'b1, 2'b01, 1'b0, 1'b0, 1'b0, 4'd0, 1'b0, 1'b1};
            op_STORE: {reg_wrD, result_srcD, mem_wrD, jumpD, branchD, alu_ctrlD, alu_srcAD, alu_srcBD} = {1'b0, 2'b00, 1'b1, 1'b0, 1'b0, 4'd0, 1'b0, 1'b1};
            op_JAL:   {reg_wrD, result_srcD, mem_wrD, jumpD, branchD, alu_ctrlD, alu_srcAD, alu_srcBD} = {1'b1, 2'b10, 1'b0, 1'b1, 1'b0, 4'd0, 1'b0, 1'b1};
            op_JALR:  {reg_wrD, result_srcD, mem_wrD, jumpD, branchD, alu_ctrlD, alu_srcAD, alu_srcBD} = {1'b1, 2'b10, 1'b0, 1'b1, 1'b0, 4'd0, 1'b0, 1'b1};
            op_LUI:   {reg_wrD, result_srcD, mem_wrD, jumpD, branchD, alu_ctrlD, alu_srcAD, alu_srcBD} = {1'b1, 2'b00, 1'b0, 1'b0, 1'b0, 4'd10,1'b0, 1'b1};
            op_AUIPC: {reg_wrD, result_srcD, mem_wrD, jumpD, branchD, alu_ctrlD, alu_srcAD, alu_srcBD} = {1'b1, 2'b00, 1'b0, 1'b0, 1'b0, 4'd0, 1'b1, 1'b1};
            default:  {reg_wrD, result_srcD, mem_wrD, jumpD, branchD, alu_ctrlD, alu_srcAD, alu_srcBD} = {1'b0, 2'b00, 1'b0, 1'b0, 1'b0, 4'd0, 1'b0, 1'b0};
        endcase
        end        
    end    
endmodule

reg_file.sv
module reg_file (
	
	input logic [31:0] i_rd_data,
	input logic [4:0] i_rd_addr,
	input logic [4:0] i_rs1_addr, 
	input logic [4:0] i_rs2_addr,	
	input logic i_rd_wren,
	input logic i_rst_n, 
	input logic i_clk, 

	output logic [31:0] o_rs1_data, 
	output logic [31:0] o_rs2_data

);

	logic [31:0] regf [31:0];	
		
	//-------------------------Read-----------------------------------
	assign	o_rs1_data = (i_rs1_addr == 0) ? 0 : regf[i_rs1_addr];
	assign	o_rs2_data = (i_rs2_addr == 0) ? 0 : regf[i_rs2_addr];
	
	//-------------------------Write----------------------------------
	always_ff @(posedge i_clk or negedge i_rst_n) begin
		if(!i_rst_n) begin
			for (int i=0; i < 32; i++)
				regf[i] <= 0;
			end
		else begin
			if((i_rd_wren == 1) && (i_rd_addr != 0))
				regf[i_rd_addr] <= i_rd_data;
			end
	end
endmodule

source/decode/imm_gen.sv
module imm_gen(
	input logic [31:0] i_instD,
	output logic [31:0] o_immExtD
);
	always_comb begin
		case(i_instD[6:0])	
				// Immediate-type
        7'b0010011: begin
			case(i_instD[14:12])
				3'b001: o_immExtD = i_instD[24:20];
				3'b101: o_immExtD = i_instD[24:20];
				default: o_immExtD = {{20{i_instD[31]}}, i_instD[31:20] };
			endcase 
			end
				// Load-type
		7'b0000011: o_immExtD = {{20{i_instD[31]}}, i_instD[31:20] };

				// Store-type
		7'b0100011: o_immExtD = {{20{i_instD[31]}}, i_instD[31:25], i_instD[11:7] };

				// Branch-type
		7'b1100011: o_immExtD = {{19{i_instD[31]}}, i_instD[31], i_instD[7], i_instD[30:25], i_instD[11:8], 1'b0};

				// Jump-type 
		7'b1100111: o_immExtD = {{20{i_instD[31]}}, i_instD[31:20]};	// JALR	- Jump and Link
		7'b1101111: o_immExtD = {{12{i_instD[31]}}, i_instD[19:12], i_instD[20], i_instD[30:21], 1'b0 };	// JAL - Jump and Link Register
	
				// Upper_immediate-type
		7'b0110111: o_immExtD = {i_instD[31:12], {12{1'b0}}};	// LUI - load upper immediate						
   		7'b0010111: o_immExtD = {i_instD[31:12], {12{1'b0}}};	// AUIPC - load upper immediate to PC	
		
		endcase
	end
endmodule

source/pipeline/decode_stage.sv
module decode_stage(
    input  logic         i_clk,
    input  logic         i_rst_n, 
    input  logic [31:0]  i_instD,
    input  logic [31:0]  i_resultW,
    input  logic [4:0]   i_rdW,
    input  logic         i_reg_wrW,

    output logic [31:0]  o_immExtD,
    output logic [31:0]  o_rs1_dataD,
    output logic [31:0]  o_rs2_dataD,
    output logic         reg_wrD,     
    output logic [1:0]   result_srcD, 
    output logic         mem_wrD,     
    output logic         jumpD,      
    output logic         branchD,    
    output logic [3:0]   alu_ctrlD,  
    output logic         alu_srcAD,
    output logic         alu_srcBD);
    imm_gen imm_gen_inst(
	    .i_instD(i_instD),
	    .o_immExtD(o_immExtD));
    reg_file reg_file_inst(
        .i_clk(i_clk),
	    .i_rst_n(i_rst_n),      	
	    .i_rd_data(i_resultW),
	    .i_rd_addr(i_rdW),                
        .i_rs1_addr(i_instD[19:15]), 
	    .i_rs2_addr(i_instD[24:20]),	
	    .i_rd_wren(i_reg_wrW),
	    .o_rs1_data(o_rs1_dataD), 
	    .o_rs2_data(o_rs2_dataD));  
    control_unit ctr_unit_inst(
        .i_op(i_instD[6:0]),
        .i_func3(i_instD[14:12]),
        .i_func7(i_instD[31:25]),
        .reg_wrD(reg_wrD),     
        .result_srcD(result_srcD), 
        .mem_wrD(mem_wrD),     
        .jumpD(jumpD),      
        .branchD(branchD),    
        .alu_ctrlD(alu_ctrlD),  
        .alu_srcAD(alu_srcAD),
        .alu_srcBD(alu_srcBD));  
endmodule

source/pipeline/decode_stage_tb.sv
`timescale 1ns/1ps

module tb_decode_stage;

    // Inputs to DUT
    logic         i_clk;
    logic         i_rst_n;
    logic [31:0]  i_instD;
    logic [31:0]  i_resultW;
    logic [4:0]   i_rdW;
    logic         i_reg_wrW;

    // Outputs from DUT
    logic [31:0]  o_immExtD;
    logic [31:0]  o_rs1_dataD;
    logic [31:0]  o_rs2_dataD;
    logic         reg_wrD;
    logic [1:0]   result_srcD;
    logic         mem_wrD;
    logic         jumpD;
    logic         branchD;
    logic [3:0]   alu_ctrlD;
    logic         alu_srcAD;
    logic         alu_srcBD;

    // Instantiate the DUT
    decode_stage dut (
        .i_clk(i_clk),
        .i_rst_n(i_rst_n),
        .i_instD(i_instD),
        .i_resultW(i_resultW),
        .i_rdW(i_rdW),
        .i_reg_wrW(i_reg_wrW),
        .o_immExtD(o_immExtD),
        .o_rs1_dataD(o_rs1_dataD),
        .o_rs2_dataD(o_rs2_dataD),
        .reg_wrD(reg_wrD),
        .result_srcD(result_srcD),
        .mem_wrD(mem_wrD),
        .jumpD(jumpD),
        .branchD(branchD),
        .alu_ctrlD(alu_ctrlD),
        .alu_srcAD(alu_srcAD),
        .alu_srcBD(alu_srcBD)
    );

    // Clock generation
    initial begin
        i_clk = 0;
        forever #5 i_clk = ~i_clk; // 100 MHz (10 ns period)
    end

    // Instruction samples (RISC-V encodings)
    // These are example encodings:
    // add x1, x2, x3   -> R-type
    localparam logic [31:0] INST_ADD  = 32'h00300B33; // add rd=1 rs1=2 rs2=3 opcode=0x33 (example)
    // addi x4, x5, 10 -> I-type
    localparam logic [31:0] INST_ADDI = 32'h00A28213; // addi rd=4 rs1=5 imm=10
    // sw x6, 8(x7)    -> S-type
    localparam logic [31:0] INST_SW   = 32'h0083A423; // sw rs2=6 rs1=7 imm=8
    // beq x1, x2, 16  -> B-type
    localparam logic [31:0] INST_BEQ  = 32'h01010663; // beq rs1=1 rs2=2 imm=16
    // jal x1, 2048    -> J-type
    localparam logic [31:0] INST_JAL  = 32'h0000_0F6F; // jal rd=1 imm=2048 (example; depends on encoding)
    // NOTE: Encodings above are illustrative; adjust if your control_unit/imm_gen expects different immediate layout.

    // Test sequence
    initial begin
        // VCD dump for waveform
        $dumpfile("tb_decode_stage.vcd");
        $dumpvars(0, tb_decode_stage);

        // initialize inputs
        i_rst_n = 0;
        i_instD = 32'h0;
        i_resultW = 32'h0;
        i_rdW = 5'd0;
        i_reg_wrW = 1'b0;

        // Hold reset for a few cycles
        repeat (4) @(posedge i_clk);
        i_rst_n = 1;

        // 1) Feed an R-type (add) instruction
        @(posedge i_clk);
        i_instD = INST_ADD;
        // No writeback yet
        i_reg_wrW = 1'b0;
        @(posedge i_clk);

        // Show outputs
        $display("[%0t] R-type: inst=0x%08h immExt=0x%08h rs1=0x%08h rs2=0x%08h reg_wr=%0b alu_ctrl=%0b",
                 $time, i_instD, o_immExtD, o_rs1_dataD, o_rs2_dataD, reg_wrD, alu_ctrlD);

        // 2) Feed an I-type (addi) instruction
        @(posedge i_clk);
        i_instD = INST_ADDI;
        @(posedge i_clk);
        $display("[%0t] I-type: inst=0x%08h immExt=0x%08h rs1=0x%08h reg_wr=%0b alu_srcBD=%0b result_src=%0b",
                 $time, i_instD, o_immExtD, o_rs1_dataD, reg_wrD, alu_srcBD, result_srcD);

        // 3) Simulate write-back to register file: write value 0xDEADBEEF to x4
        @(posedge i_clk);
        i_resultW = 32'hDEAD_BEEF;
        i_rdW = 5'd4;        // rd = x4 (matches addi rd above)
        i_reg_wrW = 1'b1;
        @(posedge i_clk);
        $display("[%0t] WB: wrote 0x%08h -> x%0d", $time, i_resultW, i_rdW);

        // disable write enable
        @(posedge i_clk); i_reg_wrW = 1'b0;

        // 4) Feed S-type (store) instruction
        @(posedge i_clk);
        i_instD = INST_SW;
        @(posedge i_clk);
        $display("[%0t] S-type: inst=0x%08h immExt=0x%08h rs1=0x%08h rs2=0x%08h mem_wr=%0b",
                 $time, i_instD, o_immExtD, o_rs1_dataD, o_rs2_dataD, mem_wrD);

        // 5) Feed B-type (branch) instruction
        @(posedge i_clk);
        i_instD = INST_BEQ;
        @(posedge i_clk);
        $display("[%0t] B-type: inst=0x%08h immExt=0x%08h branch=%0b alu_ctrl=%0b",
                 $time, i_instD, o_immExtD, branchD, alu_ctrlD);

        // 6) Feed J-type (jump) instruction
        @(posedge i_clk);
        i_instD = INST_JAL;
        @(posedge i_clk);
        $display("[%0t] J-type: inst=0x%08h immExt=0x%08h jump=%0b result_src=%0b",
                 $time, i_instD, o_immExtD, jumpD, result_srcD);

        // Finalization
        repeat (5) @(posedge i_clk);
        $display("Testbench finished at time %0t", $time);
        $finish;
    end

    // Optional: monitor at every clock edge (more verbose)
    always @(posedge i_clk) begin
        // print a short trace
        $strobe("[%0t] inst=0x%08h imm=0x%08h rs1=0x%08h rs2=0x%08h reg_wr=%0b mem_wr=%0b branch=%0b jump=%0b",
                $time, i_instD, o_immExtD, o_rs1_dataD, o_rs2_dataD, reg_wrD, mem_wrD, branchD, jumpD);
    end

endmodule

source/tb_decode_stage.vcd
$date
	Mon Nov 17 15:23:00 2025
$end
$version
	QuestaSim Version 10.2c
$end
$timescale
	1ps
$end

$scope module tb_decode_stage $end
$var parameter 32 ! INST_ADD $end
$var parameter 32 " INST_ADDI $end
$var parameter 32 # INST_SW $end
$var parameter 32 $ INST_BEQ $end
$var parameter 32 % INST_JAL $end
$var reg 1 & i_clk $end
$var reg 1 ' i_rst_n $end
$var reg 32 ( i_instD [31:0] $end
$var reg 32 ) i_resultW [31:0] $end
$var reg 5 * i_rdW [4:0] $end
$var reg 1 + i_reg_wrW $end
$var reg 32 , o_immExtD [31:0] $end
$var reg 32 - o_rs1_dataD [31:0] $end
$var reg 32 . o_rs2_dataD [31:0] $end
$var reg 1 / reg_wrD $end
$var reg 2 0 result_srcD [1:0] $end
$var reg 1 1 mem_wrD $end
$var reg 1 2 jumpD $end
$var reg 1 3 branchD $end
$var reg 4 4 alu_ctrlD [3:0] $end
$var reg 1 5 alu_srcAD $end
$var reg 1 6 alu_srcBD $end

$scope module dut $end
$var wire 1 7 i_clk $end
$var wire 1 8 i_rst_n $end
$var wire 1 9 i_instD [31] $end
$var wire 1 : i_instD [30] $end
$var wire 1 ; i_instD [29] $end
$var wire 1 < i_instD [28] $end
$var wire 1 = i_instD [27] $end
$var wire 1 > i_instD [26] $end
$var wire 1 ? i_instD [25] $end
$var wire 1 @ i_instD [24] $end
$var wire 1 A i_instD [23] $end
$var wire 1 B i_instD [22] $end
$var wire 1 C i_instD [21] $end
$var wire 1 D i_instD [20] $end
$var wire 1 E i_instD [19] $end
$var wire 1 F i_instD [18] $end
$var wire 1 G i_instD [17] $end
$var wire 1 H i_instD [16] $end
$var wire 1 I i_instD [15] $end
$var wire 1 J i_instD [14] $end
$var wire 1 K i_instD [13] $end
$var wire 1 L i_instD [12] $end
$var wire 1 M i_instD [11] $end
$var wire 1 N i_instD [10] $end
$var wire 1 O i_instD [9] $end
$var wire 1 P i_instD [8] $end
$var wire 1 Q i_instD [7] $end
$var wire 1 R i_instD [6] $end
$var wire 1 S i_instD [5] $end
$var wire 1 T i_instD [4] $end
$var wire 1 U i_instD [3] $end
$var wire 1 V i_instD [2] $end
$var wire 1 W i_instD [1] $end
$var wire 1 X i_instD [0] $end
$var wire 1 Y i_resultW [31] $end
$var wire 1 Z i_resultW [30] $end
$var wire 1 [ i_resultW [29] $end
$var wire 1 \ i_resultW [28] $end
$var wire 1 ] i_resultW [27] $end
$var wire 1 ^ i_resultW [26] $end
$var wire 1 _ i_resultW [25] $end
$var wire 1 ` i_resultW [24] $end
$var wire 1 a i_resultW [23] $end
$var wire 1 b i_resultW [22] $end
$var wire 1 c i_resultW [21] $end
$var wire 1 d i_resultW [20] $end
$var wire 1 e i_resultW [19] $end
$var wire 1 f i_resultW [18] $end
$var wire 1 g i_resultW [17] $end
$var wire 1 h i_resultW [16] $end
$var wire 1 i i_resultW [15] $end
$var wire 1 j i_resultW [14] $end
$var wire 1 k i_resultW [13] $end
$var wire 1 l i_resultW [12] $end
$var wire 1 m i_resultW [11] $end
$var wire 1 n i_resultW [10] $end
$var wire 1 o i_resultW [9] $end
$var wire 1 p i_resultW [8] $end
$var wire 1 q i_resultW [7] $end
$var wire 1 r i_resultW [6] $end
$var wire 1 s i_resultW [5] $end
$var wire 1 t i_resultW [4] $end
$var wire 1 u i_resultW [3] $end
$var wire 1 v i_resultW [2] $end
$var wire 1 w i_resultW [1] $end
$var wire 1 x i_resultW [0] $end
$var wire 1 y i_rdW [4] $end
$var wire 1 z i_rdW [3] $end
$var wire 1 { i_rdW [2] $end
$var wire 1 | i_rdW [1] $end
$var wire 1 } i_rdW [0] $end
$var wire 1 ~ i_reg_wrW $end
$var reg 32 !! o_immExtD [31:0] $end
$var reg 32 "! o_rs1_dataD [31:0] $end
$var reg 32 #! o_rs2_dataD [31:0] $end
$var reg 1 $! reg_wrD $end
$var reg 2 %! result_srcD [1:0] $end
$var reg 1 &! mem_wrD $end
$var reg 1 '! jumpD $end
$var reg 1 (! branchD $end
$var reg 4 )! alu_ctrlD [3:0] $end
$var reg 1 *! alu_srcAD $end
$var reg 1 +! alu_srcBD $end

$scope module imm_gen_inst $end
$var wire 1 9 i_instD [31] $end
$var wire 1 : i_instD [30] $end
$var wire 1 ; i_instD [29] $end
$var wire 1 < i_instD [28] $end
$var wire 1 = i_instD [27] $end
$var wire 1 > i_instD [26] $end
$var wire 1 ? i_instD [25] $end
$var wire 1 @ i_instD [24] $end
$var wire 1 A i_instD [23] $end
$var wire 1 B i_instD [22] $end
$var wire 1 C i_instD [21] $end
$var wire 1 D i_instD [20] $end
$var wire 1 E i_instD [19] $end
$var wire 1 F i_instD [18] $end
$var wire 1 G i_instD [17] $end
$var wire 1 H i_instD [16] $end
$var wire 1 I i_instD [15] $end
$var wire 1 J i_instD [14] $end
$var wire 1 K i_instD [13] $end
$var wire 1 L i_instD [12] $end
$var wire 1 M i_instD [11] $end
$var wire 1 N i_instD [10] $end
$var wire 1 O i_instD [9] $end
$var wire 1 P i_instD [8] $end
$var wire 1 Q i_instD [7] $end
$var wire 1 R i_instD [6] $end
$var wire 1 S i_instD [5] $end
$var wire 1 T i_instD [4] $end
$var wire 1 U i_instD [3] $end
$var wire 1 V i_instD [2] $end
$var wire 1 W i_instD [1] $end
$var wire 1 X i_instD [0] $end
$var reg 32 ,! o_immExtD [31:0] $end
$upscope $end

$scope module reg_file_inst $end
$var wire 1 Y i_rd_data [31] $end
$var wire 1 Z i_rd_data [30] $end
$var wire 1 [ i_rd_data [29] $end
$var wire 1 \ i_rd_data [28] $end
$var wire 1 ] i_rd_data [27] $end
$var wire 1 ^ i_rd_data [26] $end
$var wire 1 _ i_rd_data [25] $end
$var wire 1 ` i_rd_data [24] $end
$var wire 1 a i_rd_data [23] $end
$var wire 1 b i_rd_data [22] $end
$var wire 1 c i_rd_data [21] $end
$var wire 1 d i_rd_data [20] $end
$var wire 1 e i_rd_data [19] $end
$var wire 1 f i_rd_data [18] $end
$var wire 1 g i_rd_data [17] $end
$var wire 1 h i_rd_data [16] $end
$var wire 1 i i_rd_data [15] $end
$var wire 1 j i_rd_data [14] $end
$var wire 1 k i_rd_data [13] $end
$var wire 1 l i_rd_data [12] $end
$var wire 1 m i_rd_data [11] $end
$var wire 1 n i_rd_data [10] $end
$var wire 1 o i_rd_data [9] $end
$var wire 1 p i_rd_data [8] $end
$var wire 1 q i_rd_data [7] $end
$var wire 1 r i_rd_data [6] $end
$var wire 1 s i_rd_data [5] $end
$var wire 1 t i_rd_data [4] $end
$var wire 1 u i_rd_data [3] $end
$var wire 1 v i_rd_data [2] $end
$var wire 1 w i_rd_data [1] $end
$var wire 1 x i_rd_data [0] $end
$var wire 1 y i_rd_addr [4] $end
$var wire 1 z i_rd_addr [3] $end
$var wire 1 { i_rd_addr [2] $end
$var wire 1 | i_rd_addr [1] $end
$var wire 1 } i_rd_addr [0] $end
$var wire 1 E i_rs1_addr [4] $end
$var wire 1 F i_rs1_addr [3] $end
$var wire 1 G i_rs1_addr [2] $end
$var wire 1 H i_rs1_addr [1] $end
$var wire 1 I i_rs1_addr [0] $end
$var wire 1 @ i_rs2_addr [4] $end
$var wire 1 A i_rs2_addr [3] $end
$var wire 1 B i_rs2_addr [2] $end
$var wire 1 C i_rs2_addr [1] $end
$var wire 1 D i_rs2_addr [0] $end
$var wire 1 ~ i_rd_wren $end
$var wire 1 8 i_rst_n $end
$var wire 1 7 i_clk $end
$var reg 32 -! o_rs1_data [31:0] $end
$var reg 32 .! o_rs2_data [31:0] $end
$upscope $end

$scope module ctr_unit_inst $end
$var parameter 7 /! op_RTYPE $end
$var parameter 7 0! op_ITYPE $end
$var parameter 7 1! op_LOAD $end
$var parameter 7 2! op_STORE $end
$var parameter 7 3! op_BRANCH $end
$var parameter 7 4! op_JAL $end
$var parameter 7 5! op_JALR $end
$var parameter 7 6! op_LUI $end
$var parameter 7 7! op_AUIPC $end
$var parameter 4 8! func_ADD $end
$var parameter 4 9! func_SUB $end
$var parameter 4 :! func_SLL $end
$var parameter 4 ;! func_SLT $end
$var parameter 4 <! func_SLTU $end
$var parameter 4 =! func_XOR $end
$var parameter 4 >! func_SRL $end
$var parameter 4 ?! func_SRA $end
$var parameter 4 @! func_OR $end
$var parameter 4 A! func_AND $end
$var parameter 3 B! func_BEQ $end
$var parameter 3 C! func_BNE $end
$var parameter 3 D! func_BLT $end
$var parameter 3 E! func_BGE $end
$var parameter 3 F! func_BLTU $end
$var parameter 3 G! func_BGEU $end
$var wire 1 R i_op [6] $end
$var wire 1 S i_op [5] $end
$var wire 1 T i_op [4] $end
$var wire 1 U i_op [3] $end
$var wire 1 V i_op [2] $end
$var wire 1 W i_op [1] $end
$var wire 1 X i_op [0] $end
$var wire 1 J i_func3 [2] $end
$var wire 1 K i_func3 [1] $end
$var wire 1 L i_func3 [0] $end
$var wire 1 9 i_func7 [6] $end
$var wire 1 : i_func7 [5] $end
$var wire 1 ; i_func7 [4] $end
$var wire 1 < i_func7 [3] $end
$var wire 1 = i_func7 [2] $end
$var wire 1 > i_func7 [1] $end
$var wire 1 ? i_func7 [0] $end
$var reg 1 H! reg_wrD $end
$var reg 2 I! result_srcD [1:0] $end
$var reg 1 J! mem_wrD $end
$var reg 1 K! jumpD $end
$var reg 1 L! branchD $end
$var reg 4 M! alu_ctrlD [3:0] $end
$var reg 1 N! alu_srcAD $end
$var reg 1 O! alu_srcBD $end
$upscope $end
$upscope $end
$upscope $end
$enddefinitions $end
#0
$dumpvars
0&
0'
b0 (
b0 )
b0 *
0+
bx ,
b0 -
b0 .
0/
b0 0
01
02
03
b0 4
05
06
bx !!
b0 "!
b0 #!
0$!
b0 %!
0&!
0'!
0(!
b0 )!
0*!
0+!
bx ,!
b0 -!
b0 .!
0H!
b0 I!
0J!
0K!
0L!
b0 M!
0N!
0O!
b1100000000101100110011 !
b101000101000001000010011 "
b100000111010010000100011 #
b1000000010000011001100011 $
b111101101111 %
b110011 /!
b10011 0!
b11 1!
b100011 2!
b1100011 3!
b1101111 4!
b1100111 5!
b110111 6!
b10111 7!
b0 8!
b1000 9!
b1 :!
b10 ;!
b11 <!
b100 =!
b101 >!
b1101 ?!
b110 @!
b111 A!
b0 B!
b1 C!
b100 D!
b101 E!
b110 F!
b111 G!
07
08
0X
0W
0V
0U
0T
0S
0R
0Q
0P
0O
0N
0M
0L
0K
0J
0I
0H
0G
0F
0E
0D
0C
0B
0A
0@
0?
0>
0=
0<
0;
0:
09
0x
0w
0v
0u
0t
0s
0r
0q
0p
0o
0n
0m
0l
0k
0j
0i
0h
0g
0f
0e
0d
0c
0b
0a
0`
0_
0^
0]
0\
0[
0Z
0Y
0}
0|
0{
0z
0y
0~
$end
#5000
1&
17
#10000
0&
07
#15000
1&
17
#20000
0&
07
#25000
1&
17
#30000
0&
07
#35000
1&
17
1'
18
#40000
0&
07
#45000
1&
17
b1100000000101100110011 (
1X
1W
1T
1S
1P
1O
1M
1D
1C
1H!
1$!
1/
#50000
0&
07
#55000
1&
17
#60000
0&
07
#65000
1&
17
b101000101000001000010011 (
0S
0P
0M
1I
1G
0D
1A
b1010 ,!
1O!
1+!
b1010 !!
b1010 ,
16
#70000
0&
07
#75000
1&
17
#80000
0&
07
#85000
1&
17
b11011110101011011011111011101111 )
b100 *
1+
1{
1x
1w
1v
1u
1s
1r
1q
1o
1n
1m
1l
1k
1i
1h
1f
1e
1c
1a
1_
1^
1]
1\
1Z
1Y
1~
#90000
0&
07
#95000
1&
17
#100000
0&
07
#105000
1&
17
0+
0~
#110000
0&
07
#115000
1&
17
b100000111010010000100011 (
0T
1S
0O
1N
1K
1H
0C
b1000 ,!
1J!
0H!
0$!
1&!
b1000 !!
b1000 ,
11
0/
#120000
0&
07
#125000
1&
17
#130000
0&
07
#135000
1&
17
b1000000010000011001100011 (
1R
1O
0K
0I
0G
0A
1@
b1100 ,!
0O!
1L!
0J!
0&!
1(!
0+!
b1100 !!
b1100 ,
06
13
01
#140000
0&
07
#145000
1&
17
#150000
0&
07
#155000
1&
17
b111101101111 (
1V
1U
1P
1M
0H
0@
b0 ,!
1O!
0L!
1K!
b10 I!
1H!
1$!
b10 %!
1'!
0(!
1+!
b0 !!
b0 ,
16
03
12
b10 0
1/
